README.md
setup.cfg
setup.py
convolut_tensorboard/__init__.py
convolut_tensorboard/settings.py
convolut_tensorboard.egg-info/PKG-INFO
convolut_tensorboard.egg-info/SOURCES.txt
convolut_tensorboard.egg-info/dependency_links.txt
convolut_tensorboard.egg-info/not-zip-safe
convolut_tensorboard.egg-info/requires.txt
convolut_tensorboard.egg-info/top_level.txt
convolut_tensorboard/constants/__init__.py
convolut_tensorboard/constants/tensorboard_mode.py
convolut_tensorboard/logger/__init__.py
convolut_tensorboard/logger/tensorboard.py