Metadata-Version: 2.1
Name: convolut-tensorboard
Version: 0.0.2
Summary: Tensorboard integrations for convolut framework
Home-page: https://github.com/convolut/convolut-tensorboard
Author: Andrey Avdeev
Author-email: seorazer@gmail.com
License: Apache 2.0
Keywords: convolut tensorboard
Platform: UNKNOWN
Requires-Python: >=3.7
